setup.cfg
setup.py
ahonya_sika.egg-info/PKG-INFO
ahonya_sika.egg-info/SOURCES.txt
ahonya_sika.egg-info/dependency_links.txt
ahonya_sika.egg-info/requires.txt
ahonya_sika.egg-info/top_level.txt
sika/__init__.py
sika/api.py
sika/client.py
sika/config.py