Metadata-Version: 1.1
Name: ahonya-sika
Version: 0.1.1
Summary: Sika API library client for python
Home-page: https://github.com/Ahonya/sika-python
Author: Philip Adzanoukpe
Author-email: philip@ahonya.com
License: MIT
Platform: UNKNOWN
Classifier: Development Status :: 5 - Production/Stable
Classifier: Intended Audience :: Developers
Classifier: License :: OSI Approved :: MIT License
Classifier: Operating System :: OS Independent
Classifier: Programming Language :: Python :: 2.6
Classifier: Programming Language :: Python :: 2.7
Classifier: Programming Language :: Python :: 3.2
Classifier: Programming Language :: Python :: 3.3
Classifier: Topic :: Software Development :: Libraries :: Python Modules
